{
  "id": "cmi6ft0cp003p8oe8w03v4kv1",
  "filename": "ECLI:BE:RVSCE:2025:ARR.263.390.html",
  "originalName": "ECLI:BE:RVSCE:2025:ARR.263.390.html",
  "title": "ECLI:BE:RVSCE:2025:ARR.263.390",
  "ecli": "ECLI:BE:RVSCE:2025:ARR.263.390",
  "fileUrl": "https://juportal.be/content/ECLI:BE:RVSCE:2025:ARR.263.390/FR?HiLi=eNpLtDK2qs60MrAutrK0UipILM3JTM3LS1WyzrQyhIgFOIb6eLr6+bmCxIygYgh1tQCYiRQO",
  "status": "PENDING",
  "mimeType": "text/html",
  "fileSize": "0",
  "createdAt": "2025-11-19T20:10:36.937Z",
  "author": null,
  "pageCount": null,
  "language": "en"
}