{
  "id": "cmi6fsyjv000j8oe8blswmcbu",
  "filename": "ECLI:BE:CASS:2009:ARR.20090615.2.html",
  "originalName": "ECLI:BE:CASS:2009:ARR.20090615.2.html",
  "title": "ECLI:BE:CASS:2009:ARR.20090615.2",
  "ecli": "ECLI:BE:CASS:2009:ARR.20090615.2",
  "fileUrl": "https://juportal.be/content/ECLI:BE:CASS:2009:ARR.20090615.2/FR?HiLi=eNpLtDK2qs60MrAutrK0UipILM3JTM3LS1WyzrQyhIgFOIb6eLr6+bmCxIygYgh1tQCYiRQO",
  "status": "PENDING",
  "mimeType": "text/html",
  "fileSize": "0",
  "createdAt": "2025-11-19T20:10:34.603Z",
  "author": null,
  "pageCount": null,
  "language": "en"
}
